.gitignore
.gitmodules
.pre-commit-config.yaml
LICENSE
MANIFEST.in
Makefile
README.md
dev-requirements.txt
pyproject.toml
requirements.txt
setup.cfg
setup.py
.github/workflows/ci.yml
pyseq_align/__init__.py
pyseq_align/alignment.c
pyseq_align/alignment.pxd
pyseq_align/alignment.pyx
pyseq_align/needleman_wunsch.c
pyseq_align/needleman_wunsch.pyx
pyseq_align/scoring.c
pyseq_align/scoring.pxd
pyseq_align/scoring.pyx
pyseq_align/smith_waterman.c
pyseq_align/smith_waterman.pyx
pyseq_align.egg-info/PKG-INFO
pyseq_align.egg-info/SOURCES.txt
pyseq_align.egg-info/dependency_links.txt
pyseq_align.egg-info/not-zip-safe
pyseq_align.egg-info/requires.txt
pyseq_align.egg-info/top_level.txt
pyseq_align/__pycache__/__init__.cpython-38.pyc
pyseq_align/seq-align/.git
pyseq_align/seq-align/.gitignore
pyseq_align/seq-align/.gitmodules
pyseq_align/seq-align/.travis.yml
pyseq_align/seq-align/Makefile
pyseq_align/seq-align/README.md
pyseq_align/seq-align/examples/Makefile
pyseq_align/seq-align/examples/README.md
pyseq_align/seq-align/examples/nw_example.c
pyseq_align/seq-align/examples/nw_example.cpp
pyseq_align/seq-align/examples/sw_example.c
pyseq_align/seq-align/examples/sw_example.cpp
pyseq_align/seq-align/libs/Makefile
pyseq_align/seq-align/libs/seq_file/.git
pyseq_align/seq-align/libs/seq_file/.gitignore
pyseq_align/seq-align/libs/seq_file/.travis.yml
pyseq_align/seq-align/libs/seq_file/Makefile
pyseq_align/seq-align/libs/seq_file/README.md
pyseq_align/seq-align/libs/seq_file/seq_file.h
pyseq_align/seq-align/libs/seq_file/stream_buffer.h
pyseq_align/seq-align/libs/seq_file/benchmarks/Makefile
pyseq_align/seq-align/libs/seq_file/benchmarks/kseq.h
pyseq_align/seq-align/libs/seq_file/benchmarks/ktest.c
pyseq_align/seq-align/libs/seq_file/benchmarks/seq_test.c
pyseq_align/seq-align/libs/seq_file/dev/Makefile
pyseq_align/seq-align/libs/seq_file/dev/seq_cmdline.c
pyseq_align/seq-align/libs/seq_file/scripts/number-pe-reads.sh
pyseq_align/seq-align/libs/seq_file/scripts/number-reads.sh
pyseq_align/seq-align/libs/seq_file/scripts/perfect_covg.sh
pyseq_align/seq-align/libs/seq_file/test/bad.fq
pyseq_align/seq-align/libs/seq_file/test/mapped_fasta.bam
