Metadata-Version: 2.1
Name: pyseq-align
Version: 1.0.2
Summary: UNKNOWN
Home-page: https://github.com/Lioscro/pyseq-align
Author: Kyung Hoi (Joseph) Min
Author-email: phoenixter96@gmail.com
License: MIT
Platform: UNKNOWN
Classifier: Intended Audience :: Science/Research
Classifier: License :: OSI Approved :: MIT License
Classifier: Operating System :: OS Independent
Classifier: Programming Language :: Python :: 3.7
Classifier: Programming Language :: Python :: 3.8
Classifier: Programming Language :: Python :: 3.9
Classifier: Programming Language :: Cython
Classifier: Topic :: Scientific/Engineering :: Bio-Informatics
Requires-Python: >=3.6
